py_ait/__init__.py
py_ait/hf_download.py
py_ait/hf_fork.py
py_ait-0.0.43.dist-info/entry_points.txt
py_ait-0.0.43.dist-info/LICENSE
py_ait-0.0.43.dist-info/WHEEL
py_ait-0.0.43.dist-info/METADATA
py_ait-0.0.43.dist-info/RECORD
