Metadata-Version: 2.1
Name: py_ait
Version: 0.0.43
Summary: This module provide a toolbox for ai dev.
Classifier: License :: OSI Approved :: MIT License
Requires-Dist: click >=8.1.7
Requires-Dist: huggingface_hub >=0.16.4
Requires-Dist: datasets >=2.14.0
Project-URL: Documentation, https://github.com/yuanzhibang-tool/ai-toolbox
Project-URL: Source, https://github.com/yuanzhibang-tool/ai-toolbox
